<?xml version="1.0" encoding="ISO-8859-15" ?>
<SUUNTO><HEADER><MSGNAME>SDM001A</MSGNAME>
<MSGPACKING>1</MSGPACKING>
</HEADER>
<MSG><WRISTOPID>1201094</WRISTOPID>
<SAMPLECNT>148</SAMPLECNT>
<DATE>13.06.2010</DATE>
<TIME>08:57:44</TIME>
<MAXDEPTH>16.63</MAXDEPTH>
<MEANDEPTH>10.98</MEANDEPTH>
<SAMPLEINTERVAL>20</SAMPLEINTERVAL>
<LOGTITLE>37. 6/13/2010 8:57:44 AM </LOGTITLE>
<LOGNOTES></LOGNOTES>
<FOLDER></FOLDER>
<LOCATION></LOCATION>
<SITE></SITE>
<WEATHER></WEATHER>
<WATERVISIBILITY>0</WATERVISIBILITY>
<AIRTEMP>31</AIRTEMP>
<WATERTEMPMAXDEPTH>25</WATERTEMPMAXDEPTH>
<WATERTEMPATEND>26</WATERTEMPATEND>
<PARTNER></PARTNER>
<DIVEMASTER></DIVEMASTER>
<BOATNAME></BOATNAME>
<CYLINDERDESCRIPTION></CYLINDERDESCRIPTION>
<CYLINDERSIZE>12</CYLINDERSIZE>
<CYLINDERUNITS>0</CYLINDERUNITS>
<CYLINDERWORKPRESSURE>0</CYLINDERWORKPRESSURE>
<CYLINDERSTARTPRESSURE>220530</CYLINDERSTARTPRESSURE>
<CYLINDERENDPRESSURE>66340</CYLINDERENDPRESSURE>
<DIVENUMBER>37</DIVENUMBER>
<DCDIVENUMBER>1</DCDIVENUMBER>
<DIVESERIES>0</DIVESERIES>
<DEVICEMODEL>Vyper Air</DEVICEMODEL>
<DIVETIMESEC>2580</DIVETIMESEC>
<PERSONALINFO>Suunto Diver</PERSONALINFO>
<GASMODE>0</GASMODE>
<ALTMODE>0</ALTMODE>
<PMODE>0</PMODE>
<WATERVISIBILITYDESC></WATERVISIBILITYDESC>
<SACRATE>0</SACRATE>
<OLFPCT>2</OLFPCT>
<WEIGTH>0</WEIGTH>
<O2PCT>0</O2PCT>
<HEPCT_0>0</HEPCT_0>
<MIXTYPE_0>0</MIXTYPE_0>
<O2PCT_2>0</O2PCT_2>
<HEPCT_1>0</HEPCT_1>
<MIXTYPE_1>0</MIXTYPE_1>
<O2PCT_3>0</O2PCT_3>
<HEPCT_2>0</HEPCT_2>
<MIXTYPE_2>0</MIXTYPE_2>
<O2PCT_4>0</O2PCT_4>
<HEPCT_3>0</HEPCT_3>
<MIXTYPE_3>0</MIXTYPE_3>
<O2PCT_5>0</O2PCT_5>
<HEPCT_4>0</HEPCT_4>
<MIXTYPE_4>0</MIXTYPE_4>
<O2PCT_6>0</O2PCT_6>
<HEPCT_5>0</HEPCT_5>
<MIXTYPE_5>0</MIXTYPE_5>
<O2PCT_7>0</O2PCT_7>
<HEPCT_6>0</HEPCT_6>
<MIXTYPE_6>0</MIXTYPE_6>
<O2PCT_8>0</O2PCT_8>
<HEPCT_7>0</HEPCT_7>
<MIXTYPE_7>0</MIXTYPE_7>
<OTUPCT>0</OTUPCT>
<CNSPCT>0</CNSPCT>
<PO2MAX>0</PO2MAX>
<RGBMPCT>100</RGBMPCT>
<HPTRANSMITTER>1</HPTRANSMITTER>
<SURFACETIME>0</SURFACETIME>
<NOPROFILE>0</NOPROFILE>
<PREVTPRESSURE_1>0</PREVTPRESSURE_1>
<PREVTPRESSURE_2>0</PREVTPRESSURE_2>
<PREVTPRESSURE_3>0</PREVTPRESSURE_3>
<PREVTPRESSURE_4>0</PREVTPRESSURE_4>
<PREVTPRESSURE_5>0</PREVTPRESSURE_5>
<PREVTPRESSURE_6>0</PREVTPRESSURE_6>
<PREVTPRESSURE_7>0</PREVTPRESSURE_7>
<PREVTPRESSURE_8>0</PREVTPRESSURE_8>
<PREVTPRESSURE_9>0</PREVTPRESSURE_9>
<CUSTOM1></CUSTOM1>
<CUSTOM2></CUSTOM2>
<CUSTOM3></CUSTOM3>
<CUSTOM4></CUSTOM4>
<CUSTOM5></CUSTOM5>
<SAMPLE><SAMPLETIME>0</SAMPLETIME>
<DEPTH>1.26</DEPTH>
<PRESSURE>220530</PRESSURE>
<TEMPERATURE>31</TEMPERATURE>
<BOOKMARK></BOOKMARK>
<SACRATE>0</SACRATE>
<CYLPRESS>220530</CYLPRESS>
</SAMPLE>
<SAMPLE><SAMPLETIME>4</SAMPLETIME>
<DEPTH>1.2</DEPTH>
<PRESSURE>0</PRESSURE>
<TEMPERATURE>0</TEMPERATURE>
<BOOKMARK>Surface</BOOKMARK>
<BOOKMARKTYPE>125</BOOKMARKTYPE>
<SACRATE>0</SACRATE>
<CYLPRESS>0</CYLPRESS>
<OXYGENPCT>0</OXYGENPCT>
</SAMPLE>
<SAMPLE><SAMPLETIME>20</SAMPLETIME>
<DEPTH>0.2</DEPTH>
<PRESSURE>219250</PRESSURE>
<TEMPERATURE>31</TEMPERATURE>
<BOOKMARK></BOOKMARK>
<SACRATE>0</SACRATE>
<CYLPRESS>219250</CYLPRESS>
</SAMPLE>
<SAMPLE><SAMPLETIME>40</SAMPLETIME>
<DEPTH>0.23</DEPTH>
<PRESSURE>218350</PRESSURE>
<TEMPERATURE>31</TEMPERATURE>
<BOOKMARK></BOOKMARK>
<SACRATE>0</SACRATE>
<CYLPRESS>218350</CYLPRESS>
</SAMPLE>
<SAMPLE><SAMPLETIME>60</SAMPLETIME>
<DEPTH>0.27</DEPTH>
<PRESSURE>218180</PRESSURE>
<TEMPERATURE>31</TEMPERATURE>
<BOOKMARK></BOOKMARK>
<SACRATE>0</SACRATE>
<CYLPRESS>218180</CYLPRESS>
</SAMPLE>
<SAMPLE><SAMPLETIME>80</SAMPLETIME>
<DEPTH>0.24</DEPTH>
<PRESSURE>218070</PRESSURE>
<TEMPERATURE>31</TEMPERATURE>
<BOOKMARK></BOOKMARK>
<SACRATE>0</SACRATE>
<CYLPRESS>218070</CYLPRESS>
</SAMPLE>
<SAMPLE><SAMPLETIME>100</SAMPLETIME>
<DEPTH>0.21</DEPTH>
<PRESSURE>217790</PRESSURE>
<TEMPERATURE>28</TEMPERATURE>
<BOOKMARK></BOOKMARK>
<SACRATE>0</SACRATE>
<CYLPRESS>217790</CYLPRESS>
</SAMPLE>
<SAMPLE><SAMPLETIME>120</SAMPLETIME>
<DEPTH>0.23</DEPTH>
<PRESSURE>217850</PRESSURE>
<TEMPERATURE>28</TEMPERATURE>
<BOOKMARK></BOOKMARK>
<SACRATE>0</SACRATE>
<CYLPRESS>217850</CYLPRESS>
</SAMPLE>
<SAMPLE><SAMPLETIME>140</SAMPLETIME>
<DEPTH>0.24</DEPTH>
<PRESSURE>217600</PRESSURE>
<TEMPERATURE>28</TEMPERATURE>
<BOOKMARK></BOOKMARK>
<SACRATE>0</SACRATE>
<CYLPRESS>217600</CYLPRESS>
</SAMPLE>
<SAMPLE><SAMPLETIME>160</SAMPLETIME>
<DEPTH>0.25</DEPTH>
<PRESSURE>216880</PRESSURE>
<TEMPERATURE>28</TEMPERATURE>
<BOOKMARK></BOOKMARK>
<SACRATE>0</SACRATE>
<CYLPRESS>216880</CYLPRESS>
</SAMPLE>
<SAMPLE><SAMPLETIME>180</SAMPLETIME>
<DEPTH>0.23</DEPTH>
<PRESSURE>216810</PRESSURE>
<TEMPERATURE>28</TEMPERATURE>
<BOOKMARK></BOOKMARK>
<SACRATE>0</SACRATE>
<CYLPRESS>216810</CYLPRESS>
</SAMPLE>
<SAMPLE><SAMPLETIME>200</SAMPLETIME>
<DEPTH>0.22</DEPTH>
<PRESSURE>216790</PRESSURE>
<TEMPERATURE>27</TEMPERATURE>
<BOOKMARK></BOOKMARK>
<SACRATE>0</SACRATE>
<CYLPRESS>216790</CYLPRESS>
</SAMPLE>
<SAMPLE><SAMPLETIME>220</SAMPLETIME>
<DEPTH>0.3</DEPTH>
<PRESSURE>216830</PRESSURE>
<TEMPERATURE>27</TEMPERATURE>
<BOOKMARK></BOOKMARK>
<SACRATE>0</SACRATE>
<CYLPRESS>216830</CYLPRESS>
</SAMPLE>
<SAMPLE><SAMPLETIME>239</SAMPLETIME>
<DEPTH>1.2</DEPTH>
<PRESSURE>0</PRESSURE>
<TEMPERATURE>0</TEMPERATURE>
<BOOKMARK>Surface</BOOKMARK>
<BOOKMARKTYPE>125</BOOKMARKTYPE>
<SACRATE>0</SACRATE>
<CYLPRESS>0</CYLPRESS>
<OXYGENPCT>0</OXYGENPCT>
</SAMPLE>
<SAMPLE><SAMPLETIME>240</SAMPLETIME>
<DEPTH>1.13</DEPTH>
<PRESSURE>215890</PRESSURE>
<TEMPERATURE>27</TEMPERATURE>
<BOOKMARK></BOOKMARK>
<SACRATE>0</SACRATE>
<CYLPRESS>215890</CYLPRESS>
</SAMPLE>
<SAMPLE><SAMPLETIME>241</SAMPLETIME>
<DEPTH>1.2</DEPTH>
<PRESSURE>0</PRESSURE>
<TEMPERATURE>0</TEMPERATURE>
<BOOKMARK>Surface</BOOKMARK>
<BOOKMARKTYPE>125</BOOKMARKTYPE>
<SACRATE>0</SACRATE>
<CYLPRESS>0</CYLPRESS>
<OXYGENPCT>0</OXYGENPCT>
</SAMPLE>
<SAMPLE><SAMPLETIME>260</SAMPLETIME>
<DEPTH>3.74</DEPTH>
<PRESSURE>214330</PRESSURE>
<TEMPERATURE>27</TEMPERATURE>
<BOOKMARK></BOOKMARK>
<SACRATE>0</SACRATE>
<CYLPRESS>214330</CYLPRESS>
</SAMPLE>
<SAMPLE><SAMPLETIME>280</SAMPLETIME>
<DEPTH>3.42</DEPTH>
<PRESSURE>213170</PRESSURE>
<TEMPERATURE>27</TEMPERATURE>
<BOOKMARK></BOOKMARK>
<SACRATE>0</SACRATE>
<CYLPRESS>213170</CYLPRESS>
</SAMPLE>
<SAMPLE><SAMPLETIME>300</SAMPLETIME>
<DEPTH>5.09</DEPTH>
<PRESSURE>211320</PRESSURE>
<TEMPERATURE>27</TEMPERATURE>
<BOOKMARK></BOOKMARK>
<SACRATE>0</SACRATE>
<CYLPRESS>211320</CYLPRESS>
</SAMPLE>
<SAMPLE><SAMPLETIME>320</SAMPLETIME>
<DEPTH>5.58</DEPTH>
<PRESSURE>209580</PRESSURE>
<TEMPERATURE>27</TEMPERATURE>
<BOOKMARK></BOOKMARK>
<SACRATE>0</SACRATE>
<CYLPRESS>209580</CYLPRESS>
</SAMPLE>
<SAMPLE><SAMPLETIME>340</SAMPLETIME>
<DEPTH>6.25</DEPTH>
<PRESSURE>208380</PRESSURE>
<TEMPERATURE>27</TEMPERATURE>
<BOOKMARK></BOOKMARK>
<SACRATE>0</SACRATE>
<CYLPRESS>208380</CYLPRESS>
</SAMPLE>
<SAMPLE><SAMPLETIME>360</SAMPLETIME>
<DEPTH>7.25</DEPTH>
<PRESSURE>206830</PRESSURE>
<TEMPERATURE>27</TEMPERATURE>
<BOOKMARK></BOOKMARK>
<SACRATE>0</SACRATE>
<CYLPRESS>206830</CYLPRESS>
</SAMPLE>
<SAMPLE><SAMPLETIME>380</SAMPLETIME>
<DEPTH>7.94</DEPTH>
<PRESSURE>205310</PRESSURE>
<TEMPERATURE>27</TEMPERATURE>
<BOOKMARK></BOOKMARK>
<SACRATE>0</SACRATE>
<CYLPRESS>205310</CYLPRESS>
</SAMPLE>
<SAMPLE><SAMPLETIME>400</SAMPLETIME>
<DEPTH>8.69</DEPTH>
<PRESSURE>204180</PRESSURE>
<TEMPERATURE>26</TEMPERATURE>
<BOOKMARK></BOOKMARK>
<SACRATE>0</SACRATE>
<CYLPRESS>204180</CYLPRESS>
</SAMPLE>
<SAMPLE><SAMPLETIME>420</SAMPLETIME>
<DEPTH>8.89</DEPTH>
<PRESSURE>203190</PRESSURE>
<TEMPERATURE>26</TEMPERATURE>
<BOOKMARK></BOOKMARK>
<SACRATE>0</SACRATE>
<CYLPRESS>203190</CYLPRESS>
</SAMPLE>
<SAMPLE><SAMPLETIME>440</SAMPLETIME>
<DEPTH>9.85</DEPTH>
<PRESSURE>202570</PRESSURE>
<TEMPERATURE>26</TEMPERATURE>
<BOOKMARK></BOOKMARK>
<SACRATE>0</SACRATE>
<CYLPRESS>202570</CYLPRESS>
</SAMPLE>
<SAMPLE><SAMPLETIME>460</SAMPLETIME>
<DEPTH>10.08</DEPTH>
<PRESSURE>201620</PRESSURE>
<TEMPERATURE>26</TEMPERATURE>
<BOOKMARK></BOOKMARK>
<SACRATE>0</SACRATE>
<CYLPRESS>201620</CYLPRESS>
</SAMPLE>
<SAMPLE><SAMPLETIME>480</SAMPLETIME>
<DEPTH>10.12</DEPTH>
<PRESSURE>201620</PRESSURE>
<TEMPERATURE>26</TEMPERATURE>
<BOOKMARK></BOOKMARK>
<SACRATE>0</SACRATE>
<CYLPRESS>201620</CYLPRESS>
</SAMPLE>
<SAMPLE><SAMPLETIME>500</SAMPLETIME>
<DEPTH>10.04</DEPTH>
<PRESSURE>199000</PRESSURE>
<TEMPERATURE>26</TEMPERATURE>
<BOOKMARK></BOOKMARK>
<SACRATE>0</SACRATE>
<CYLPRESS>199000</CYLPRESS>
</SAMPLE>
<SAMPLE><SAMPLETIME>520</SAMPLETIME>
<DEPTH>9.96</DEPTH>
<PRESSURE>198790</PRESSURE>
<TEMPERATURE>26</TEMPERATURE>
<BOOKMARK></BOOKMARK>
<SACRATE>0</SACRATE>
<CYLPRESS>198790</CYLPRESS>
</SAMPLE>
<SAMPLE><SAMPLETIME>540</SAMPLETIME>
<DEPTH>10.01</DEPTH>
<PRESSURE>198790</PRESSURE>
<TEMPERATURE>26</TEMPERATURE>
<BOOKMARK></BOOKMARK>
<SACRATE>0</SACRATE>
<CYLPRESS>198790</CYLPRESS>
</SAMPLE>
<SAMPLE><SAMPLETIME>560</SAMPLETIME>
<DEPTH>8.88</DEPTH>
<PRESSURE>197910</PRESSURE>
<TEMPERATURE>26</TEMPERATURE>
<BOOKMARK></BOOKMARK>
<SACRATE>0</SACRATE>
<CYLPRESS>197910</CYLPRESS>
</SAMPLE>
<SAMPLE><SAMPLETIME>580</SAMPLETIME>
<DEPTH>8.3</DEPTH>
<PRESSURE>195080</PRESSURE>
<TEMPERATURE>26</TEMPERATURE>
<BOOKMARK></BOOKMARK>
<SACRATE>0</SACRATE>
<CYLPRESS>195080</CYLPRESS>
</SAMPLE>
<SAMPLE><SAMPLETIME>600</SAMPLETIME>
<DEPTH>8.19</DEPTH>
<PRESSURE>194370</PRESSURE>
<TEMPERATURE>26</TEMPERATURE>
<BOOKMARK></BOOKMARK>
<SACRATE>0</SACRATE>
<CYLPRESS>194370</CYLPRESS>
</SAMPLE>
<SAMPLE><SAMPLETIME>620</SAMPLETIME>
<DEPTH>7.75</DEPTH>
<PRESSURE>193340</PRESSURE>
<TEMPERATURE>26</TEMPERATURE>
<BOOKMARK></BOOKMARK>
<SACRATE>0</SACRATE>
<CYLPRESS>193340</CYLPRESS>
</SAMPLE>
<SAMPLE><SAMPLETIME>640</SAMPLETIME>
<DEPTH>7.97</DEPTH>
<PRESSURE>193340</PRESSURE>
<TEMPERATURE>26</TEMPERATURE>
<BOOKMARK></BOOKMARK>
<SACRATE>0</SACRATE>
<CYLPRESS>193340</CYLPRESS>
</SAMPLE>
<SAMPLE><SAMPLETIME>660</SAMPLETIME>
<DEPTH>9.14</DEPTH>
<PRESSURE>191700</PRESSURE>
<TEMPERATURE>26</TEMPERATURE>
<BOOKMARK></BOOKMARK>
<SACRATE>0</SACRATE>
<CYLPRESS>191700</CYLPRESS>
</SAMPLE>
<SAMPLE><SAMPLETIME>680</SAMPLETIME>
<DEPTH>11.21</DEPTH>
<PRESSURE>190510</PRESSURE>
<TEMPERATURE>26</TEMPERATURE>
<BOOKMARK></BOOKMARK>
<SACRATE>0</SACRATE>
<CYLPRESS>190510</CYLPRESS>
</SAMPLE>
<SAMPLE><SAMPLETIME>700</SAMPLETIME>
<DEPTH>11.7</DEPTH>
<PRESSURE>189260</PRESSURE>
<TEMPERATURE>25</TEMPERATURE>
<BOOKMARK></BOOKMARK>
<SACRATE>0</SACRATE>
<CYLPRESS>189260</CYLPRESS>
</SAMPLE>
<SAMPLE><SAMPLETIME>720</SAMPLETIME>
<DEPTH>12.11</DEPTH>
<PRESSURE>189260</PRESSURE>
<TEMPERATURE>25</TEMPERATURE>
<BOOKMARK></BOOKMARK>
<SACRATE>0</SACRATE>
<CYLPRESS>189260</CYLPRESS>
</SAMPLE>
<SAMPLE><SAMPLETIME>740</SAMPLETIME>
<DEPTH>12.39</DEPTH>
<PRESSURE>189260</PRESSURE>
<TEMPERATURE>25</TEMPERATURE>
<BOOKMARK></BOOKMARK>
<SACRATE>0</SACRATE>
<CYLPRESS>189260</CYLPRESS>
</SAMPLE>
<SAMPLE><SAMPLETIME>760</SAMPLETIME>
<DEPTH>12.67</DEPTH>
<PRESSURE>187710</PRESSURE>
<TEMPERATURE>25</TEMPERATURE>
<BOOKMARK></BOOKMARK>
<SACRATE>0</SACRATE>
<CYLPRESS>187710</CYLPRESS>
</SAMPLE>
<SAMPLE><SAMPLETIME>780</SAMPLETIME>
<DEPTH>13.22</DEPTH>
<PRESSURE>185370</PRESSURE>
<TEMPERATURE>25</TEMPERATURE>
<BOOKMARK></BOOKMARK>
<SACRATE>0</SACRATE>
<CYLPRESS>185370</CYLPRESS>
</SAMPLE>
<SAMPLE><SAMPLETIME>800</SAMPLETIME>
<DEPTH>13.73</DEPTH>
<PRESSURE>182630</PRESSURE>
<TEMPERATURE>25</TEMPERATURE>
<BOOKMARK></BOOKMARK>
<SACRATE>0</SACRATE>
<CYLPRESS>182630</CYLPRESS>
</SAMPLE>
<SAMPLE><SAMPLETIME>820</SAMPLETIME>
<DEPTH>14.27</DEPTH>
<PRESSURE>181750</PRESSURE>
<TEMPERATURE>25</TEMPERATURE>
<BOOKMARK></BOOKMARK>
<SACRATE>0</SACRATE>
<CYLPRESS>181750</CYLPRESS>
</SAMPLE>
<SAMPLE><SAMPLETIME>840</SAMPLETIME>
<DEPTH>13.67</DEPTH>
<PRESSURE>181750</PRESSURE>
<TEMPERATURE>25</TEMPERATURE>
<BOOKMARK></BOOKMARK>
<SACRATE>0</SACRATE>
<CYLPRESS>181750</CYLPRESS>
</SAMPLE>
<SAMPLE><SAMPLETIME>860</SAMPLETIME>
<DEPTH>13.47</DEPTH>
<PRESSURE>180070</PRESSURE>
<TEMPERATURE>25</TEMPERATURE>
<BOOKMARK></BOOKMARK>
<SACRATE>0</SACRATE>
<CYLPRESS>180070</CYLPRESS>
</SAMPLE>
<SAMPLE><SAMPLETIME>880</SAMPLETIME>
<DEPTH>12.91</DEPTH>
<PRESSURE>178050</PRESSURE>
<TEMPERATURE>25</TEMPERATURE>
<BOOKMARK></BOOKMARK>
<SACRATE>0</SACRATE>
<CYLPRESS>178050</CYLPRESS>
</SAMPLE>
<SAMPLE><SAMPLETIME>900</SAMPLETIME>
<DEPTH>13.64</DEPTH>
<PRESSURE>176830</PRESSURE>
<TEMPERATURE>25</TEMPERATURE>
<BOOKMARK></BOOKMARK>
<SACRATE>0</SACRATE>
<CYLPRESS>176830</CYLPRESS>
</SAMPLE>
<SAMPLE><SAMPLETIME>920</SAMPLETIME>
<DEPTH>13.97</DEPTH>
<PRESSURE>175580</PRESSURE>
<TEMPERATURE>25</TEMPERATURE>
<BOOKMARK></BOOKMARK>
<SACRATE>0</SACRATE>
<CYLPRESS>175580</CYLPRESS>
</SAMPLE>
<SAMPLE><SAMPLETIME>940</SAMPLETIME>
<DEPTH>14.12</DEPTH>
<PRESSURE>175580</PRESSURE>
<TEMPERATURE>25</TEMPERATURE>
<BOOKMARK></BOOKMARK>
<SACRATE>0</SACRATE>
<CYLPRESS>175580</CYLPRESS>
</SAMPLE>
<SAMPLE><SAMPLETIME>960</SAMPLETIME>
<DEPTH>14.54</DEPTH>
<PRESSURE>174000</PRESSURE>
<TEMPERATURE>25</TEMPERATURE>
<BOOKMARK></BOOKMARK>
<SACRATE>0</SACRATE>
<CYLPRESS>174000</CYLPRESS>
</SAMPLE>
<SAMPLE><SAMPLETIME>980</SAMPLETIME>
<DEPTH>13.29</DEPTH>
<PRESSURE>172790</PRESSURE>
<TEMPERATURE>25</TEMPERATURE>
<BOOKMARK></BOOKMARK>
<SACRATE>0</SACRATE>
<CYLPRESS>172790</CYLPRESS>
</SAMPLE>
<SAMPLE><SAMPLETIME>1000</SAMPLETIME>
<DEPTH>13.91</DEPTH>
<PRESSURE>171260</PRESSURE>
<TEMPERATURE>25</TEMPERATURE>
<BOOKMARK></BOOKMARK>
<SACRATE>0</SACRATE>
<CYLPRESS>171260</CYLPRESS>
</SAMPLE>
<SAMPLE><SAMPLETIME>1020</SAMPLETIME>
<DEPTH>15.15</DEPTH>
<PRESSURE>168530</PRESSURE>
<TEMPERATURE>25</TEMPERATURE>
<BOOKMARK></BOOKMARK>
<SACRATE>0</SACRATE>
<CYLPRESS>168530</CYLPRESS>
</SAMPLE>
<SAMPLE><SAMPLETIME>1040</SAMPLETIME>
<DEPTH>15.02</DEPTH>
<PRESSURE>167580</PRESSURE>
<TEMPERATURE>25</TEMPERATURE>
<BOOKMARK></BOOKMARK>
<SACRATE>0</SACRATE>
<CYLPRESS>167580</CYLPRESS>
</SAMPLE>
<SAMPLE><SAMPLETIME>1060</SAMPLETIME>
<DEPTH>15.45</DEPTH>
<PRESSURE>166040</PRESSURE>
<TEMPERATURE>25</TEMPERATURE>
<BOOKMARK></BOOKMARK>
<SACRATE>0</SACRATE>
<CYLPRESS>166040</CYLPRESS>
</SAMPLE>
<SAMPLE><SAMPLETIME>1080</SAMPLETIME>
<DEPTH>14.94</DEPTH>
<PRESSURE>164830</PRESSURE>
<TEMPERATURE>25</TEMPERATURE>
<BOOKMARK></BOOKMARK>
<SACRATE>0</SACRATE>
<CYLPRESS>164830</CYLPRESS>
</SAMPLE>
<SAMPLE><SAMPLETIME>1100</SAMPLETIME>
<DEPTH>15.23</DEPTH>
<PRESSURE>164150</PRESSURE>
<TEMPERATURE>25</TEMPERATURE>
<BOOKMARK></BOOKMARK>
<SACRATE>0</SACRATE>
<CYLPRESS>164150</CYLPRESS>
</SAMPLE>
<SAMPLE><SAMPLETIME>1120</SAMPLETIME>
<DEPTH>15.58</DEPTH>
<PRESSURE>162870</PRESSURE>
<TEMPERATURE>25</TEMPERATURE>
<BOOKMARK></BOOKMARK>
<SACRATE>0</SACRATE>
<CYLPRESS>162870</CYLPRESS>
</SAMPLE>
<SAMPLE><SAMPLETIME>1140</SAMPLETIME>
<DEPTH>15.32</DEPTH>
<PRESSURE>161840</PRESSURE>
<TEMPERATURE>25</TEMPERATURE>
<BOOKMARK></BOOKMARK>
<SACRATE>0</SACRATE>
<CYLPRESS>161840</CYLPRESS>
</SAMPLE>
<SAMPLE><SAMPLETIME>1160</SAMPLETIME>
<DEPTH>15.46</DEPTH>
<PRESSURE>160660</PRESSURE>
<TEMPERATURE>25</TEMPERATURE>
<BOOKMARK></BOOKMARK>
<SACRATE>0</SACRATE>
<CYLPRESS>160660</CYLPRESS>
</SAMPLE>
<SAMPLE><SAMPLETIME>1180</SAMPLETIME>
<DEPTH>15.92</DEPTH>
<PRESSURE>159150</PRESSURE>
<TEMPERATURE>25</TEMPERATURE>
<BOOKMARK></BOOKMARK>
<SACRATE>0</SACRATE>
<CYLPRESS>159150</CYLPRESS>
</SAMPLE>
<SAMPLE><SAMPLETIME>1200</SAMPLETIME>
<DEPTH>15.43</DEPTH>
<PRESSURE>159150</PRESSURE>
<TEMPERATURE>25</TEMPERATURE>
<BOOKMARK></BOOKMARK>
<SACRATE>0</SACRATE>
<CYLPRESS>159150</CYLPRESS>
</SAMPLE>
<SAMPLE><SAMPLETIME>1220</SAMPLETIME>
<DEPTH>14.92</DEPTH>
<PRESSURE>155860</PRESSURE>
<TEMPERATURE>25</TEMPERATURE>
<BOOKMARK></BOOKMARK>
<SACRATE>0</SACRATE>
<CYLPRESS>155860</CYLPRESS>
</SAMPLE>
<SAMPLE><SAMPLETIME>1240</SAMPLETIME>
<DEPTH>13.05</DEPTH>
<PRESSURE>154660</PRESSURE>
<TEMPERATURE>25</TEMPERATURE>
<BOOKMARK></BOOKMARK>
<SACRATE>0</SACRATE>
<CYLPRESS>154660</CYLPRESS>
</SAMPLE>
<SAMPLE><SAMPLETIME>1260</SAMPLETIME>
<DEPTH>14.57</DEPTH>
<PRESSURE>154660</PRESSURE>
<TEMPERATURE>25</TEMPERATURE>
<BOOKMARK></BOOKMARK>
<SACRATE>0</SACRATE>
<CYLPRESS>154660</CYLPRESS>
</SAMPLE>
<SAMPLE><SAMPLETIME>1280</SAMPLETIME>
<DEPTH>16.2</DEPTH>
<PRESSURE>152400</PRESSURE>
<TEMPERATURE>25</TEMPERATURE>
<BOOKMARK></BOOKMARK>
<SACRATE>0</SACRATE>
<CYLPRESS>152400</CYLPRESS>
</SAMPLE>
<SAMPLE><SAMPLETIME>1300</SAMPLETIME>
<DEPTH>15.82</DEPTH>
<PRESSURE>152400</PRESSURE>
<TEMPERATURE>25</TEMPERATURE>
<BOOKMARK></BOOKMARK>
<SACRATE>0</SACRATE>
<CYLPRESS>152400</CYLPRESS>
</SAMPLE>
<SAMPLE><SAMPLETIME>1320</SAMPLETIME>
<DEPTH>15.24</DEPTH>
<PRESSURE>151110</PRESSURE>
<TEMPERATURE>25</TEMPERATURE>
<BOOKMARK></BOOKMARK>
<SACRATE>0</SACRATE>
<CYLPRESS>151110</CYLPRESS>
</SAMPLE>
<SAMPLE><SAMPLETIME>1340</SAMPLETIME>
<DEPTH>15.26</DEPTH>
<PRESSURE>151110</PRESSURE>
<TEMPERATURE>25</TEMPERATURE>
<BOOKMARK></BOOKMARK>
<SACRATE>0</SACRATE>
<CYLPRESS>151110</CYLPRESS>
</SAMPLE>
<SAMPLE><SAMPLETIME>1360</SAMPLETIME>
<DEPTH>15.41</DEPTH>
<PRESSURE>146070</PRESSURE>
<TEMPERATURE>25</TEMPERATURE>
<BOOKMARK></BOOKMARK>
<SACRATE>0</SACRATE>
<CYLPRESS>146070</CYLPRESS>
</SAMPLE>
<SAMPLE><SAMPLETIME>1380</SAMPLETIME>
<DEPTH>15.17</DEPTH>
<PRESSURE>144250</PRESSURE>
<TEMPERATURE>25</TEMPERATURE>
<BOOKMARK></BOOKMARK>
<SACRATE>0</SACRATE>
<CYLPRESS>144250</CYLPRESS>
</SAMPLE>
<SAMPLE><SAMPLETIME>1400</SAMPLETIME>
<DEPTH>15.27</DEPTH>
<PRESSURE>143710</PRESSURE>
<TEMPERATURE>25</TEMPERATURE>
<BOOKMARK></BOOKMARK>
<SACRATE>0</SACRATE>
<CYLPRESS>143710</CYLPRESS>
</SAMPLE>
<SAMPLE><SAMPLETIME>1420</SAMPLETIME>
<DEPTH>14.56</DEPTH>
<PRESSURE>142310</PRESSURE>
<TEMPERATURE>25</TEMPERATURE>
<BOOKMARK></BOOKMARK>
<SACRATE>0</SACRATE>
<CYLPRESS>142310</CYLPRESS>
</SAMPLE>
<SAMPLE><SAMPLETIME>1440</SAMPLETIME>
<DEPTH>13.52</DEPTH>
<PRESSURE>139930</PRESSURE>
<TEMPERATURE>25</TEMPERATURE>
<BOOKMARK></BOOKMARK>
<SACRATE>0</SACRATE>
<CYLPRESS>139930</CYLPRESS>
</SAMPLE>
<SAMPLE><SAMPLETIME>1460</SAMPLETIME>
<DEPTH>13.88</DEPTH>
<PRESSURE>139720</PRESSURE>
<TEMPERATURE>25</TEMPERATURE>
<BOOKMARK></BOOKMARK>
<SACRATE>0</SACRATE>
<CYLPRESS>139720</CYLPRESS>
</SAMPLE>
<SAMPLE><SAMPLETIME>1480</SAMPLETIME>
<DEPTH>13.97</DEPTH>
<PRESSURE>138490</PRESSURE>
<TEMPERATURE>25</TEMPERATURE>
<BOOKMARK></BOOKMARK>
<SACRATE>0</SACRATE>
<CYLPRESS>138490</CYLPRESS>
</SAMPLE>
<SAMPLE><SAMPLETIME>1500</SAMPLETIME>
<DEPTH>15.04</DEPTH>
<PRESSURE>136910</PRESSURE>
<TEMPERATURE>25</TEMPERATURE>
<BOOKMARK></BOOKMARK>
<SACRATE>0</SACRATE>
<CYLPRESS>136910</CYLPRESS>
</SAMPLE>
<SAMPLE><SAMPLETIME>1520</SAMPLETIME>
<DEPTH>15.32</DEPTH>
<PRESSURE>135060</PRESSURE>
<TEMPERATURE>25</TEMPERATURE>
<BOOKMARK></BOOKMARK>
<SACRATE>0</SACRATE>
<CYLPRESS>135060</CYLPRESS>
</SAMPLE>
<SAMPLE><SAMPLETIME>1540</SAMPLETIME>
<DEPTH>15.38</DEPTH>
<PRESSURE>133400</PRESSURE>
<TEMPERATURE>25</TEMPERATURE>
<BOOKMARK></BOOKMARK>
<SACRATE>0</SACRATE>
<CYLPRESS>133400</CYLPRESS>
</SAMPLE>
<SAMPLE><SAMPLETIME>1560</SAMPLETIME>
<DEPTH>14.06</DEPTH>
<PRESSURE>133280</PRESSURE>
<TEMPERATURE>25</TEMPERATURE>
<BOOKMARK></BOOKMARK>
<SACRATE>0</SACRATE>
<CYLPRESS>133280</CYLPRESS>
</SAMPLE>
<SAMPLE><SAMPLETIME>1580</SAMPLETIME>
<DEPTH>13.45</DEPTH>
<PRESSURE>132160</PRESSURE>
<TEMPERATURE>25</TEMPERATURE>
<BOOKMARK></BOOKMARK>
<SACRATE>0</SACRATE>
<CYLPRESS>132160</CYLPRESS>
</SAMPLE>
<SAMPLE><SAMPLETIME>1600</SAMPLETIME>
<DEPTH>13.09</DEPTH>
<PRESSURE>132160</PRESSURE>
<TEMPERATURE>25</TEMPERATURE>
<BOOKMARK></BOOKMARK>
<SACRATE>0</SACRATE>
<CYLPRESS>132160</CYLPRESS>
</SAMPLE>
<SAMPLE><SAMPLETIME>1620</SAMPLETIME>
<DEPTH>11.24</DEPTH>
<PRESSURE>129620</PRESSURE>
<TEMPERATURE>25</TEMPERATURE>
<BOOKMARK></BOOKMARK>
<SACRATE>0</SACRATE>
<CYLPRESS>129620</CYLPRESS>
</SAMPLE>
<SAMPLE><SAMPLETIME>1640</SAMPLETIME>
<DEPTH>12.43</DEPTH>
<PRESSURE>127110</PRESSURE>
<TEMPERATURE>25</TEMPERATURE>
<BOOKMARK></BOOKMARK>
<SACRATE>0</SACRATE>
<CYLPRESS>127110</CYLPRESS>
</SAMPLE>
<SAMPLE><SAMPLETIME>1660</SAMPLETIME>
<DEPTH>13.77</DEPTH>
<PRESSURE>124160</PRESSURE>
<TEMPERATURE>25</TEMPERATURE>
<BOOKMARK></BOOKMARK>
<SACRATE>0</SACRATE>
<CYLPRESS>124160</CYLPRESS>
</SAMPLE>
<SAMPLE><SAMPLETIME>1680</SAMPLETIME>
<DEPTH>11.78</DEPTH>
<PRESSURE>123140</PRESSURE>
<TEMPERATURE>25</TEMPERATURE>
<BOOKMARK></BOOKMARK>
<SACRATE>0</SACRATE>
<CYLPRESS>123140</CYLPRESS>
</SAMPLE>
<SAMPLE><SAMPLETIME>1700</SAMPLETIME>
<DEPTH>10.6</DEPTH>
<PRESSURE>123140</PRESSURE>
<TEMPERATURE>25</TEMPERATURE>
<BOOKMARK></BOOKMARK>
<SACRATE>0</SACRATE>
<CYLPRESS>123140</CYLPRESS>
</SAMPLE>
<SAMPLE><SAMPLETIME>1720</SAMPLETIME>
<DEPTH>11.74</DEPTH>
<PRESSURE>121500</PRESSURE>
<TEMPERATURE>25</TEMPERATURE>
<BOOKMARK></BOOKMARK>
<SACRATE>0</SACRATE>
<CYLPRESS>121500</CYLPRESS>
</SAMPLE>
<SAMPLE><SAMPLETIME>1740</SAMPLETIME>
<DEPTH>12.78</DEPTH>
<PRESSURE>121380</PRESSURE>
<TEMPERATURE>25</TEMPERATURE>
<BOOKMARK></BOOKMARK>
<SACRATE>0</SACRATE>
<CYLPRESS>121380</CYLPRESS>
</SAMPLE>
<SAMPLE><SAMPLETIME>1760</SAMPLETIME>
<DEPTH>12.45</DEPTH>
<PRESSURE>120560</PRESSURE>
<TEMPERATURE>25</TEMPERATURE>
<BOOKMARK></BOOKMARK>
<SACRATE>0</SACRATE>
<CYLPRESS>120560</CYLPRESS>
</SAMPLE>
<SAMPLE><SAMPLETIME>1780</SAMPLETIME>
<DEPTH>12.11</DEPTH>
<PRESSURE>117200</PRESSURE>
<TEMPERATURE>25</TEMPERATURE>
<BOOKMARK></BOOKMARK>
<SACRATE>0</SACRATE>
<CYLPRESS>117200</CYLPRESS>
</SAMPLE>
<SAMPLE><SAMPLETIME>1800</SAMPLETIME>
<DEPTH>12.14</DEPTH>
<PRESSURE>116600</PRESSURE>
<TEMPERATURE>25</TEMPERATURE>
<BOOKMARK></BOOKMARK>
<SACRATE>0</SACRATE>
<CYLPRESS>116600</CYLPRESS>
</SAMPLE>
<SAMPLE><SAMPLETIME>1820</SAMPLETIME>
<DEPTH>12.76</DEPTH>
<PRESSURE>116140</PRESSURE>
<TEMPERATURE>25</TEMPERATURE>
<BOOKMARK></BOOKMARK>
<SACRATE>0</SACRATE>
<CYLPRESS>116140</CYLPRESS>
</SAMPLE>
<SAMPLE><SAMPLETIME>1840</SAMPLETIME>
<DEPTH>12.4</DEPTH>
<PRESSURE>114900</PRESSURE>
<TEMPERATURE>25</TEMPERATURE>
<BOOKMARK></BOOKMARK>
<SACRATE>0</SACRATE>
<CYLPRESS>114900</CYLPRESS>
</SAMPLE>
<SAMPLE><SAMPLETIME>1860</SAMPLETIME>
<DEPTH>12.35</DEPTH>
<PRESSURE>113400</PRESSURE>
<TEMPERATURE>25</TEMPERATURE>
<BOOKMARK></BOOKMARK>
<SACRATE>0</SACRATE>
<CYLPRESS>113400</CYLPRESS>
</SAMPLE>
<SAMPLE><SAMPLETIME>1880</SAMPLETIME>
<DEPTH>12.12</DEPTH>
<PRESSURE>112320</PRESSURE>
<TEMPERATURE>25</TEMPERATURE>
<BOOKMARK></BOOKMARK>
<SACRATE>0</SACRATE>
<CYLPRESS>112320</CYLPRESS>
</SAMPLE>
<SAMPLE><SAMPLETIME>1900</SAMPLETIME>
<DEPTH>13.13</DEPTH>
<PRESSURE>111200</PRESSURE>
<TEMPERATURE>25</TEMPERATURE>
<BOOKMARK></BOOKMARK>
<SACRATE>0</SACRATE>
<CYLPRESS>111200</CYLPRESS>
</SAMPLE>
<SAMPLE><SAMPLETIME>1920</SAMPLETIME>
<DEPTH>12.67</DEPTH>
<PRESSURE>111010</PRESSURE>
<TEMPERATURE>25</TEMPERATURE>
<BOOKMARK></BOOKMARK>
<SACRATE>0</SACRATE>
<CYLPRESS>111010</CYLPRESS>
</SAMPLE>
<SAMPLE><SAMPLETIME>1940</SAMPLETIME>
<DEPTH>12.74</DEPTH>
<PRESSURE>109430</PRESSURE>
<TEMPERATURE>25</TEMPERATURE>
<BOOKMARK></BOOKMARK>
<SACRATE>0</SACRATE>
<CYLPRESS>109430</CYLPRESS>
</SAMPLE>
<SAMPLE><SAMPLETIME>1960</SAMPLETIME>
<DEPTH>13.06</DEPTH>
<PRESSURE>108160</PRESSURE>
<TEMPERATURE>25</TEMPERATURE>
<BOOKMARK></BOOKMARK>
<SACRATE>0</SACRATE>
<CYLPRESS>108160</CYLPRESS>
</SAMPLE>
<SAMPLE><SAMPLETIME>1980</SAMPLETIME>
<DEPTH>12.75</DEPTH>
<PRESSURE>107200</PRESSURE>
<TEMPERATURE>25</TEMPERATURE>
<BOOKMARK></BOOKMARK>
<SACRATE>0</SACRATE>
<CYLPRESS>107200</CYLPRESS>
</SAMPLE>
<SAMPLE><SAMPLETIME>2000</SAMPLETIME>
<DEPTH>12.46</DEPTH>
<PRESSURE>105800</PRESSURE>
<TEMPERATURE>25</TEMPERATURE>
<BOOKMARK></BOOKMARK>
<SACRATE>0</SACRATE>
<CYLPRESS>105800</CYLPRESS>
</SAMPLE>
<SAMPLE><SAMPLETIME>2020</SAMPLETIME>
<DEPTH>12.67</DEPTH>
<PRESSURE>104620</PRESSURE>
<TEMPERATURE>25</TEMPERATURE>
<BOOKMARK></BOOKMARK>
<SACRATE>0</SACRATE>
<CYLPRESS>104620</CYLPRESS>
</SAMPLE>
<SAMPLE><SAMPLETIME>2040</SAMPLETIME>
<DEPTH>11.83</DEPTH>
<PRESSURE>104050</PRESSURE>
<TEMPERATURE>25</TEMPERATURE>
<BOOKMARK></BOOKMARK>
<SACRATE>0</SACRATE>
<CYLPRESS>104050</CYLPRESS>
</SAMPLE>
<SAMPLE><SAMPLETIME>2060</SAMPLETIME>
<DEPTH>11.44</DEPTH>
<PRESSURE>103080</PRESSURE>
<TEMPERATURE>25</TEMPERATURE>
<BOOKMARK></BOOKMARK>
<SACRATE>0</SACRATE>
<CYLPRESS>103080</CYLPRESS>
</SAMPLE>
<SAMPLE><SAMPLETIME>2080</SAMPLETIME>
<DEPTH>11.25</DEPTH>
<PRESSURE>101740</PRESSURE>
<TEMPERATURE>25</TEMPERATURE>
<BOOKMARK></BOOKMARK>
<SACRATE>0</SACRATE>
<CYLPRESS>101740</CYLPRESS>
</SAMPLE>
<SAMPLE><SAMPLETIME>2100</SAMPLETIME>
<DEPTH>10.49</DEPTH>
<PRESSURE>100940</PRESSURE>
<TEMPERATURE>25</TEMPERATURE>
<BOOKMARK></BOOKMARK>
<SACRATE>0</SACRATE>
<CYLPRESS>100940</CYLPRESS>
</SAMPLE>
<SAMPLE><SAMPLETIME>2120</SAMPLETIME>
<DEPTH>9.52</DEPTH>
<PRESSURE>100230</PRESSURE>
<TEMPERATURE>25</TEMPERATURE>
<BOOKMARK></BOOKMARK>
<SACRATE>0</SACRATE>
<CYLPRESS>100230</CYLPRESS>
</SAMPLE>
<SAMPLE><SAMPLETIME>2140</SAMPLETIME>
<DEPTH>10.05</DEPTH>
<PRESSURE>99150</PRESSURE>
<TEMPERATURE>25</TEMPERATURE>
<BOOKMARK></BOOKMARK>
<SACRATE>0</SACRATE>
<CYLPRESS>99150</CYLPRESS>
</SAMPLE>
<SAMPLE><SAMPLETIME>2160</SAMPLETIME>
<DEPTH>9.91</DEPTH>
<PRESSURE>98100</PRESSURE>
<TEMPERATURE>25</TEMPERATURE>
<BOOKMARK></BOOKMARK>
<SACRATE>0</SACRATE>
<CYLPRESS>98100</CYLPRESS>
</SAMPLE>
<SAMPLE><SAMPLETIME>2180</SAMPLETIME>
<DEPTH>9.19</DEPTH>
<PRESSURE>97410</PRESSURE>
<TEMPERATURE>25</TEMPERATURE>
<BOOKMARK></BOOKMARK>
<SACRATE>0</SACRATE>
<CYLPRESS>97410</CYLPRESS>
</SAMPLE>
<SAMPLE><SAMPLETIME>2200</SAMPLETIME>
<DEPTH>8.17</DEPTH>
<PRESSURE>96390</PRESSURE>
<TEMPERATURE>25</TEMPERATURE>
<BOOKMARK></BOOKMARK>
<SACRATE>0</SACRATE>
<CYLPRESS>96390</CYLPRESS>
</SAMPLE>
<SAMPLE><SAMPLETIME>2220</SAMPLETIME>
<DEPTH>8.64</DEPTH>
<PRESSURE>95470</PRESSURE>
<TEMPERATURE>25</TEMPERATURE>
<BOOKMARK></BOOKMARK>
<SACRATE>0</SACRATE>
<CYLPRESS>95470</CYLPRESS>
</SAMPLE>
<SAMPLE><SAMPLETIME>2240</SAMPLETIME>
<DEPTH>8.68</DEPTH>
<PRESSURE>94480</PRESSURE>
<TEMPERATURE>25</TEMPERATURE>
<BOOKMARK></BOOKMARK>
<SACRATE>0</SACRATE>
<CYLPRESS>94480</CYLPRESS>
</SAMPLE>
<SAMPLE><SAMPLETIME>2260</SAMPLETIME>
<DEPTH>8.32</DEPTH>
<PRESSURE>93980</PRESSURE>
<TEMPERATURE>25</TEMPERATURE>
<BOOKMARK></BOOKMARK>
<SACRATE>0</SACRATE>
<CYLPRESS>93980</CYLPRESS>
</SAMPLE>
<SAMPLE><SAMPLETIME>2280</SAMPLETIME>
<DEPTH>8.1</DEPTH>
<PRESSURE>93360</PRESSURE>
<TEMPERATURE>25</TEMPERATURE>
<BOOKMARK></BOOKMARK>
<SACRATE>0</SACRATE>
<CYLPRESS>93360</CYLPRESS>
</SAMPLE>
<SAMPLE><SAMPLETIME>2300</SAMPLETIME>
<DEPTH>8.07</DEPTH>
<PRESSURE>91980</PRESSURE>
<TEMPERATURE>25</TEMPERATURE>
<BOOKMARK></BOOKMARK>
<SACRATE>0</SACRATE>
<CYLPRESS>91980</CYLPRESS>
</SAMPLE>
<SAMPLE><SAMPLETIME>2320</SAMPLETIME>
<DEPTH>7.27</DEPTH>
<PRESSURE>91020</PRESSURE>
<TEMPERATURE>25</TEMPERATURE>
<BOOKMARK></BOOKMARK>
<SACRATE>0</SACRATE>
<CYLPRESS>91020</CYLPRESS>
</SAMPLE>
<SAMPLE><SAMPLETIME>2340</SAMPLETIME>
<DEPTH>7.73</DEPTH>
<PRESSURE>89960</PRESSURE>
<TEMPERATURE>25</TEMPERATURE>
<BOOKMARK></BOOKMARK>
<SACRATE>0</SACRATE>
<CYLPRESS>89960</CYLPRESS>
</SAMPLE>
<SAMPLE><SAMPLETIME>2360</SAMPLETIME>
<DEPTH>7.56</DEPTH>
<PRESSURE>89060</PRESSURE>
<TEMPERATURE>25</TEMPERATURE>
<BOOKMARK></BOOKMARK>
<SACRATE>0</SACRATE>
<CYLPRESS>89060</CYLPRESS>
</SAMPLE>
<SAMPLE><SAMPLETIME>2380</SAMPLETIME>
<DEPTH>9.01</DEPTH>
<PRESSURE>88030</PRESSURE>
<TEMPERATURE>25</TEMPERATURE>
<BOOKMARK></BOOKMARK>
<SACRATE>0</SACRATE>
<CYLPRESS>88030</CYLPRESS>
</SAMPLE>
<SAMPLE><SAMPLETIME>2400</SAMPLETIME>
<DEPTH>10.74</DEPTH>
<PRESSURE>86860</PRESSURE>
<TEMPERATURE>25</TEMPERATURE>
<BOOKMARK></BOOKMARK>
<SACRATE>0</SACRATE>
<CYLPRESS>86860</CYLPRESS>
</SAMPLE>
<SAMPLE><SAMPLETIME>2420</SAMPLETIME>
<DEPTH>11.5</DEPTH>
<PRESSURE>85580</PRESSURE>
<TEMPERATURE>25</TEMPERATURE>
<BOOKMARK></BOOKMARK>
<SACRATE>0</SACRATE>
<CYLPRESS>85580</CYLPRESS>
</SAMPLE>
<SAMPLE><SAMPLETIME>2440</SAMPLETIME>
<DEPTH>11.6</DEPTH>
<PRESSURE>84300</PRESSURE>
<TEMPERATURE>25</TEMPERATURE>
<BOOKMARK></BOOKMARK>
<SACRATE>0</SACRATE>
<CYLPRESS>84300</CYLPRESS>
</SAMPLE>
<SAMPLE><SAMPLETIME>2460</SAMPLETIME>
<DEPTH>11.45</DEPTH>
<PRESSURE>83750</PRESSURE>
<TEMPERATURE>25</TEMPERATURE>
<BOOKMARK></BOOKMARK>
<SACRATE>0</SACRATE>
<CYLPRESS>83750</CYLPRESS>
</SAMPLE>
<SAMPLE><SAMPLETIME>2480</SAMPLETIME>
<DEPTH>12.09</DEPTH>
<PRESSURE>82620</PRESSURE>
<TEMPERATURE>25</TEMPERATURE>
<BOOKMARK></BOOKMARK>
<SACRATE>0</SACRATE>
<CYLPRESS>82620</CYLPRESS>
</SAMPLE>
<SAMPLE><SAMPLETIME>2500</SAMPLETIME>
<DEPTH>12.22</DEPTH>
<PRESSURE>82230</PRESSURE>
<TEMPERATURE>25</TEMPERATURE>
<BOOKMARK></BOOKMARK>
<SACRATE>0</SACRATE>
<CYLPRESS>82230</CYLPRESS>
</SAMPLE>
<SAMPLE><SAMPLETIME>2520</SAMPLETIME>
<DEPTH>12.14</DEPTH>
<PRESSURE>82230</PRESSURE>
<TEMPERATURE>25</TEMPERATURE>
<BOOKMARK></BOOKMARK>
<SACRATE>0</SACRATE>
<CYLPRESS>82230</CYLPRESS>
</SAMPLE>
<SAMPLE><SAMPLETIME>2540</SAMPLETIME>
<DEPTH>12.18</DEPTH>
<PRESSURE>79830</PRESSURE>
<TEMPERATURE>25</TEMPERATURE>
<BOOKMARK></BOOKMARK>
<SACRATE>0</SACRATE>
<CYLPRESS>79830</CYLPRESS>
</SAMPLE>
<SAMPLE><SAMPLETIME>2560</SAMPLETIME>
<DEPTH>10.48</DEPTH>
<PRESSURE>78990</PRESSURE>
<TEMPERATURE>25</TEMPERATURE>
<BOOKMARK></BOOKMARK>
<SACRATE>0</SACRATE>
<CYLPRESS>78990</CYLPRESS>
</SAMPLE>
<SAMPLE><SAMPLETIME>2580</SAMPLETIME>
<DEPTH>10.05</DEPTH>
<PRESSURE>77760</PRESSURE>
<TEMPERATURE>25</TEMPERATURE>
<BOOKMARK></BOOKMARK>
<SACRATE>0</SACRATE>
<CYLPRESS>77760</CYLPRESS>
</SAMPLE>
<SAMPLE><SAMPLETIME>2600</SAMPLETIME>
<DEPTH>9.5</DEPTH>
<PRESSURE>76800</PRESSURE>
<TEMPERATURE>25</TEMPERATURE>
<BOOKMARK></BOOKMARK>
<SACRATE>0</SACRATE>
<CYLPRESS>76800</CYLPRESS>
</SAMPLE>
<SAMPLE><SAMPLETIME>2620</SAMPLETIME>
<DEPTH>7.61</DEPTH>
<PRESSURE>76130</PRESSURE>
<TEMPERATURE>25</TEMPERATURE>
<BOOKMARK></BOOKMARK>
<SACRATE>0</SACRATE>
<CYLPRESS>76130</CYLPRESS>
</SAMPLE>
<SAMPLE><SAMPLETIME>2640</SAMPLETIME>
<DEPTH>6.46</DEPTH>
<PRESSURE>75200</PRESSURE>
<TEMPERATURE>25</TEMPERATURE>
<BOOKMARK></BOOKMARK>
<SACRATE>0</SACRATE>
<CYLPRESS>75200</CYLPRESS>
</SAMPLE>
<SAMPLE><SAMPLETIME>2660</SAMPLETIME>
<DEPTH>4.98</DEPTH>
<PRESSURE>74460</PRESSURE>
<TEMPERATURE>25</TEMPERATURE>
<BOOKMARK></BOOKMARK>
<SACRATE>0</SACRATE>
<CYLPRESS>74460</CYLPRESS>
</SAMPLE>
<SAMPLE><SAMPLETIME>2680</SAMPLETIME>
<DEPTH>5.13</DEPTH>
<PRESSURE>73370</PRESSURE>
<TEMPERATURE>25</TEMPERATURE>
<BOOKMARK></BOOKMARK>
<SACRATE>0</SACRATE>
<CYLPRESS>73370</CYLPRESS>
</SAMPLE>
<SAMPLE><SAMPLETIME>2700</SAMPLETIME>
<DEPTH>3.91</DEPTH>
<PRESSURE>72880</PRESSURE>
<TEMPERATURE>26</TEMPERATURE>
<BOOKMARK></BOOKMARK>
<SACRATE>0</SACRATE>
<CYLPRESS>72880</CYLPRESS>
</SAMPLE>
<SAMPLE><SAMPLETIME>2720</SAMPLETIME>
<DEPTH>4.35</DEPTH>
<PRESSURE>71940</PRESSURE>
<TEMPERATURE>26</TEMPERATURE>
<BOOKMARK></BOOKMARK>
<SACRATE>0</SACRATE>
<CYLPRESS>71940</CYLPRESS>
</SAMPLE>
<SAMPLE><SAMPLETIME>2740</SAMPLETIME>
<DEPTH>4.46</DEPTH>
<PRESSURE>70830</PRESSURE>
<TEMPERATURE>26</TEMPERATURE>
<BOOKMARK></BOOKMARK>
<SACRATE>0</SACRATE>
<CYLPRESS>70830</CYLPRESS>
</SAMPLE>
<SAMPLE><SAMPLETIME>2760</SAMPLETIME>
<DEPTH>4.82</DEPTH>
<PRESSURE>70260</PRESSURE>
<TEMPERATURE>26</TEMPERATURE>
<BOOKMARK></BOOKMARK>
<SACRATE>0</SACRATE>
<CYLPRESS>70260</CYLPRESS>
</SAMPLE>
<SAMPLE><SAMPLETIME>2780</SAMPLETIME>
<DEPTH>3.95</DEPTH>
<PRESSURE>69630</PRESSURE>
<TEMPERATURE>26</TEMPERATURE>
<BOOKMARK></BOOKMARK>
<SACRATE>0</SACRATE>
<CYLPRESS>69630</CYLPRESS>
</SAMPLE>
<SAMPLE><SAMPLETIME>2800</SAMPLETIME>
<DEPTH>4.5</DEPTH>
<PRESSURE>68810</PRESSURE>
<TEMPERATURE>26</TEMPERATURE>
<BOOKMARK></BOOKMARK>
<SACRATE>0</SACRATE>
<CYLPRESS>68810</CYLPRESS>
</SAMPLE>
<SAMPLE><SAMPLETIME>2820</SAMPLETIME>
<DEPTH>4.02</DEPTH>
<PRESSURE>68230</PRESSURE>
<TEMPERATURE>26</TEMPERATURE>
<BOOKMARK></BOOKMARK>
<SACRATE>0</SACRATE>
<CYLPRESS>68230</CYLPRESS>
</SAMPLE>
<SAMPLE><SAMPLETIME>2840</SAMPLETIME>
<DEPTH>4.08</DEPTH>
<PRESSURE>67180</PRESSURE>
<TEMPERATURE>26</TEMPERATURE>
<BOOKMARK></BOOKMARK>
<SACRATE>0</SACRATE>
<CYLPRESS>67180</CYLPRESS>
</SAMPLE>
<SAMPLE><SAMPLETIME>2860</SAMPLETIME>
<DEPTH>1.73</DEPTH>
<PRESSURE>66340</PRESSURE>
<TEMPERATURE>26</TEMPERATURE>
<BOOKMARK></BOOKMARK>
<SACRATE>0</SACRATE>
<CYLPRESS>66340</CYLPRESS>
</SAMPLE>
<SAMPLE><SAMPLETIME>2866</SAMPLETIME>
<DEPTH>1.2</DEPTH>
<PRESSURE>0</PRESSURE>
<TEMPERATURE>0</TEMPERATURE>
<BOOKMARK>Surface</BOOKMARK>
<BOOKMARKTYPE>125</BOOKMARKTYPE>
<SACRATE>0</SACRATE>
<CYLPRESS>0</CYLPRESS>
<OXYGENPCT>0</OXYGENPCT>
</SAMPLE>
</MSG>
</SUUNTO>
