<?xml version="1.0" encoding="ISO-8859-15" ?>
<SUUNTO><HEADER><MSGNAME>SDM001A</MSGNAME>
<MSGPACKING>1</MSGPACKING>
</HEADER>
<MSG><WRISTOPID>1201094</WRISTOPID>
<SAMPLECNT>39</SAMPLECNT>
<DATE>16.05.2011</DATE>
<TIME>12:52:06</TIME>
<MAXDEPTH>10.47</MAXDEPTH>
<MEANDEPTH>5.69</MEANDEPTH>
<SAMPLEINTERVAL>20</SAMPLEINTERVAL>
<LOGTITLE>116. 5/16/2011 12:52:06 PM </LOGTITLE>
<LOGNOTES></LOGNOTES>
<FOLDER></FOLDER>
<LOCATION></LOCATION>
<SITE></SITE>
<WEATHER></WEATHER>
<WATERVISIBILITY>0</WATERVISIBILITY>
<AIRTEMP>12</AIRTEMP>
<WATERTEMPMAXDEPTH>9</WATERTEMPMAXDEPTH>
<WATERTEMPATEND>10</WATERTEMPATEND>
<PARTNER></PARTNER>
<DIVEMASTER></DIVEMASTER>
<BOATNAME></BOATNAME>
<CYLINDERDESCRIPTION></CYLINDERDESCRIPTION>
<CYLINDERSIZE>12</CYLINDERSIZE>
<CYLINDERUNITS>0</CYLINDERUNITS>
<CYLINDERWORKPRESSURE>0</CYLINDERWORKPRESSURE>
<CYLINDERSTARTPRESSURE>91520</CYLINDERSTARTPRESSURE>
<CYLINDERENDPRESSURE>63700</CYLINDERENDPRESSURE>
<DIVENUMBER>116</DIVENUMBER>
<DCDIVENUMBER>2</DCDIVENUMBER>
<DIVESERIES>0</DIVESERIES>
<DEVICEMODEL>Vyper Air</DEVICEMODEL>
<DIVETIMESEC>720</DIVETIMESEC>
<PERSONALINFO>Suunto Diver</PERSONALINFO>
<GASMODE>0</GASMODE>
<ALTMODE>0</ALTMODE>
<PMODE>0</PMODE>
<WATERVISIBILITYDESC></WATERVISIBILITYDESC>
<SACRATE>0</SACRATE>
<OLFPCT>0</OLFPCT>
<WEIGTH>0</WEIGTH>
<O2PCT>0</O2PCT>
<HEPCT_0>0</HEPCT_0>
<MIXTYPE_0>0</MIXTYPE_0>
<O2PCT_2>0</O2PCT_2>
<HEPCT_1>0</HEPCT_1>
<MIXTYPE_1>0</MIXTYPE_1>
<O2PCT_3>0</O2PCT_3>
<HEPCT_2>0</HEPCT_2>
<MIXTYPE_2>0</MIXTYPE_2>
<O2PCT_4>0</O2PCT_4>
<HEPCT_3>0</HEPCT_3>
<MIXTYPE_3>0</MIXTYPE_3>
<O2PCT_5>0</O2PCT_5>
<HEPCT_4>0</HEPCT_4>
<MIXTYPE_4>0</MIXTYPE_4>
<O2PCT_6>0</O2PCT_6>
<HEPCT_5>0</HEPCT_5>
<MIXTYPE_5>0</MIXTYPE_5>
<O2PCT_7>0</O2PCT_7>
<HEPCT_6>0</HEPCT_6>
<MIXTYPE_6>0</MIXTYPE_6>
<O2PCT_8>0</O2PCT_8>
<HEPCT_7>0</HEPCT_7>
<MIXTYPE_7>0</MIXTYPE_7>
<OTUPCT>3</OTUPCT>
<CNSPCT>5</CNSPCT>
<PO2MAX>0</PO2MAX>
<RGBMPCT>100</RGBMPCT>
<HPTRANSMITTER>1</HPTRANSMITTER>
<SURFACETIME>540</SURFACETIME>
<NOPROFILE>0</NOPROFILE>
<PREVTPRESSURE_1>9.5</PREVTPRESSURE_1>
<PREVTPRESSURE_2>16.81</PREVTPRESSURE_2>
<PREVTPRESSURE_3>19.35</PREVTPRESSURE_3>
<PREVTPRESSURE_4>15.93</PREVTPRESSURE_4>
<PREVTPRESSURE_5>10.56</PREVTPRESSURE_5>
<PREVTPRESSURE_6>6.07</PREVTPRESSURE_6>
<PREVTPRESSURE_7>4.27</PREVTPRESSURE_7>
<PREVTPRESSURE_8>2.22</PREVTPRESSURE_8>
<PREVTPRESSURE_9>1.13</PREVTPRESSURE_9>
<CUSTOM1></CUSTOM1>
<CUSTOM2></CUSTOM2>
<CUSTOM3></CUSTOM3>
<CUSTOM4></CUSTOM4>
<CUSTOM5></CUSTOM5>
<SAMPLE><SAMPLETIME>0</SAMPLETIME>
<DEPTH>1.26</DEPTH>
<PRESSURE>91520</PRESSURE>
<TEMPERATURE>12</TEMPERATURE>
<BOOKMARK></BOOKMARK>
<SACRATE>6.67</SACRATE>
<CYLPRESS>91520</CYLPRESS>
</SAMPLE>
<SAMPLE><SAMPLETIME>20</SAMPLETIME>
<DEPTH>1.8</DEPTH>
<PRESSURE>90880</PRESSURE>
<TEMPERATURE>12</TEMPERATURE>
<BOOKMARK></BOOKMARK>
<SACRATE>11.68</SACRATE>
<CYLPRESS>90880</CYLPRESS>
</SAMPLE>
<SAMPLE><SAMPLETIME>40</SAMPLETIME>
<DEPTH>2.66</DEPTH>
<PRESSURE>89800</PRESSURE>
<TEMPERATURE>12</TEMPERATURE>
<BOOKMARK></BOOKMARK>
<SACRATE>13.36</SACRATE>
<CYLPRESS>89800</CYLPRESS>
</SAMPLE>
<SAMPLE><SAMPLETIME>60</SAMPLETIME>
<DEPTH>3.56</DEPTH>
<PRESSURE>88930</PRESSURE>
<TEMPERATURE>12</TEMPERATURE>
<BOOKMARK></BOOKMARK>
<SACRATE>17.56</SACRATE>
<CYLPRESS>88930</CYLPRESS>
</SAMPLE>
<SAMPLE><SAMPLETIME>80</SAMPLETIME>
<DEPTH>3.52</DEPTH>
<PRESSURE>88630</PRESSURE>
<TEMPERATURE>12</TEMPERATURE>
<BOOKMARK></BOOKMARK>
<SACRATE>22.62</SACRATE>
<CYLPRESS>88630</CYLPRESS>
</SAMPLE>
<SAMPLE><SAMPLETIME>100</SAMPLETIME>
<DEPTH>3.93</DEPTH>
<PRESSURE>87870</PRESSURE>
<TEMPERATURE>11</TEMPERATURE>
<BOOKMARK></BOOKMARK>
<SACRATE>19.76</SACRATE>
<CYLPRESS>87870</CYLPRESS>
</SAMPLE>
<SAMPLE><SAMPLETIME>120</SAMPLETIME>
<DEPTH>4.82</DEPTH>
<PRESSURE>86910</PRESSURE>
<TEMPERATURE>11</TEMPERATURE>
<BOOKMARK></BOOKMARK>
<SACRATE>18.54</SACRATE>
<CYLPRESS>86910</CYLPRESS>
</SAMPLE>
<SAMPLE><SAMPLETIME>140</SAMPLETIME>
<DEPTH>5.38</DEPTH>
<PRESSURE>86150</PRESSURE>
<TEMPERATURE>11</TEMPERATURE>
<BOOKMARK></BOOKMARK>
<SACRATE>22.18</SACRATE>
<CYLPRESS>86150</CYLPRESS>
</SAMPLE>
<SAMPLE><SAMPLETIME>160</SAMPLETIME>
<DEPTH>6.2</DEPTH>
<PRESSURE>85360</PRESSURE>
<TEMPERATURE>11</TEMPERATURE>
<BOOKMARK></BOOKMARK>
<SACRATE>21.71</SACRATE>
<CYLPRESS>85360</CYLPRESS>
</SAMPLE>
<SAMPLE><SAMPLETIME>180</SAMPLETIME>
<DEPTH>6.94</DEPTH>
<PRESSURE>84200</PRESSURE>
<TEMPERATURE>11</TEMPERATURE>
<BOOKMARK></BOOKMARK>
<SACRATE>18.2</SACRATE>
<CYLPRESS>84200</CYLPRESS>
</SAMPLE>
<SAMPLE><SAMPLETIME>200</SAMPLETIME>
<DEPTH>7.3</DEPTH>
<PRESSURE>83360</PRESSURE>
<TEMPERATURE>10</TEMPERATURE>
<BOOKMARK></BOOKMARK>
<SACRATE>18.41</SACRATE>
<CYLPRESS>83360</CYLPRESS>
</SAMPLE>
<SAMPLE><SAMPLETIME>220</SAMPLETIME>
<DEPTH>7.97</DEPTH>
<PRESSURE>83000</PRESSURE>
<TEMPERATURE>10</TEMPERATURE>
<BOOKMARK></BOOKMARK>
<SACRATE>18.69</SACRATE>
<CYLPRESS>83000</CYLPRESS>
</SAMPLE>
<SAMPLE><SAMPLETIME>240</SAMPLETIME>
<DEPTH>9.11</DEPTH>
<PRESSURE>82020</PRESSURE>
<TEMPERATURE>10</TEMPERATURE>
<BOOKMARK></BOOKMARK>
<SACRATE>15.69</SACRATE>
<CYLPRESS>82020</CYLPRESS>
</SAMPLE>
<SAMPLE><SAMPLETIME>260</SAMPLETIME>
<DEPTH>9.7</DEPTH>
<PRESSURE>80980</PRESSURE>
<TEMPERATURE>10</TEMPERATURE>
<BOOKMARK></BOOKMARK>
<SACRATE>15.68</SACRATE>
<CYLPRESS>80980</CYLPRESS>
</SAMPLE>
<SAMPLE><SAMPLETIME>280</SAMPLETIME>
<DEPTH>9.92</DEPTH>
<PRESSURE>80380</PRESSURE>
<TEMPERATURE>10</TEMPERATURE>
<BOOKMARK></BOOKMARK>
<SACRATE>17.31</SACRATE>
<CYLPRESS>80380</CYLPRESS>
</SAMPLE>
<SAMPLE><SAMPLETIME>300</SAMPLETIME>
<DEPTH>9.89</DEPTH>
<PRESSURE>79410</PRESSURE>
<TEMPERATURE>9</TEMPERATURE>
<BOOKMARK></BOOKMARK>
<SACRATE>15.35</SACRATE>
<CYLPRESS>79410</CYLPRESS>
</SAMPLE>
<SAMPLE><SAMPLETIME>320</SAMPLETIME>
<DEPTH>10.33</DEPTH>
<PRESSURE>78570</PRESSURE>
<TEMPERATURE>9</TEMPERATURE>
<BOOKMARK></BOOKMARK>
<SACRATE>13.67</SACRATE>
<CYLPRESS>78570</CYLPRESS>
</SAMPLE>
<SAMPLE><SAMPLETIME>340</SAMPLETIME>
<DEPTH>10.46</DEPTH>
<PRESSURE>78020</PRESSURE>
<TEMPERATURE>9</TEMPERATURE>
<BOOKMARK></BOOKMARK>
<SACRATE>16.05</SACRATE>
<CYLPRESS>78020</CYLPRESS>
</SAMPLE>
<SAMPLE><SAMPLETIME>360</SAMPLETIME>
<DEPTH>9.72</DEPTH>
<PRESSURE>77390</PRESSURE>
<TEMPERATURE>9</TEMPERATURE>
<BOOKMARK></BOOKMARK>
<SACRATE>17.5</SACRATE>
<CYLPRESS>77390</CYLPRESS>
</SAMPLE>
<SAMPLE><SAMPLETIME>380</SAMPLETIME>
<DEPTH>9.09</DEPTH>
<PRESSURE>76200</PRESSURE>
<TEMPERATURE>9</TEMPERATURE>
<BOOKMARK></BOOKMARK>
<SACRATE>18.83</SACRATE>
<CYLPRESS>76200</CYLPRESS>
</SAMPLE>
<SAMPLE><SAMPLETIME>400</SAMPLETIME>
<DEPTH>8.06</DEPTH>
<PRESSURE>74940</PRESSURE>
<TEMPERATURE>9</TEMPERATURE>
<BOOKMARK></BOOKMARK>
<SACRATE>19.81</SACRATE>
<CYLPRESS>74940</CYLPRESS>
</SAMPLE>
<SAMPLE><SAMPLETIME>420</SAMPLETIME>
<DEPTH>7.45</DEPTH>
<PRESSURE>73890</PRESSURE>
<TEMPERATURE>9</TEMPERATURE>
<BOOKMARK></BOOKMARK>
<SACRATE>21.86</SACRATE>
<CYLPRESS>73890</CYLPRESS>
</SAMPLE>
<SAMPLE><SAMPLETIME>440</SAMPLETIME>
<DEPTH>6.67</DEPTH>
<PRESSURE>73210</PRESSURE>
<TEMPERATURE>9</TEMPERATURE>
<BOOKMARK></BOOKMARK>
<SACRATE>21.84</SACRATE>
<CYLPRESS>73210</CYLPRESS>
</SAMPLE>
<SAMPLE><SAMPLETIME>460</SAMPLETIME>
<DEPTH>5.66</DEPTH>
<PRESSURE>72270</PRESSURE>
<TEMPERATURE>9</TEMPERATURE>
<BOOKMARK></BOOKMARK>
<SACRATE>20.8</SACRATE>
<CYLPRESS>72270</CYLPRESS>
</SAMPLE>
<SAMPLE><SAMPLETIME>480</SAMPLETIME>
<DEPTH>4.82</DEPTH>
<PRESSURE>71340</PRESSURE>
<TEMPERATURE>9</TEMPERATURE>
<BOOKMARK></BOOKMARK>
<SACRATE>18.34</SACRATE>
<CYLPRESS>71340</CYLPRESS>
</SAMPLE>
<SAMPLE><SAMPLETIME>500</SAMPLETIME>
<DEPTH>5.05</DEPTH>
<PRESSURE>70530</PRESSURE>
<TEMPERATURE>9</TEMPERATURE>
<BOOKMARK></BOOKMARK>
<SACRATE>17.55</SACRATE>
<CYLPRESS>70530</CYLPRESS>
</SAMPLE>
<SAMPLE><SAMPLETIME>520</SAMPLETIME>
<DEPTH>4.59</DEPTH>
<PRESSURE>70130</PRESSURE>
<TEMPERATURE>9</TEMPERATURE>
<BOOKMARK></BOOKMARK>
<SACRATE>18.89</SACRATE>
<CYLPRESS>70130</CYLPRESS>
</SAMPLE>
<SAMPLE><SAMPLETIME>540</SAMPLETIME>
<DEPTH>3.87</DEPTH>
<PRESSURE>69710</PRESSURE>
<TEMPERATURE>9</TEMPERATURE>
<BOOKMARK></BOOKMARK>
<SACRATE>16.84</SACRATE>
<CYLPRESS>69710</CYLPRESS>
</SAMPLE>
<SAMPLE><SAMPLETIME>560</SAMPLETIME>
<DEPTH>3.91</DEPTH>
<PRESSURE>68660</PRESSURE>
<TEMPERATURE>9</TEMPERATURE>
<BOOKMARK></BOOKMARK>
<SACRATE>15.04</SACRATE>
<CYLPRESS>68660</CYLPRESS>
</SAMPLE>
<SAMPLE><SAMPLETIME>580</SAMPLETIME>
<DEPTH>4.18</DEPTH>
<PRESSURE>68180</PRESSURE>
<TEMPERATURE>9</TEMPERATURE>
<BOOKMARK></BOOKMARK>
<SACRATE>15.89</SACRATE>
<CYLPRESS>68180</CYLPRESS>
</SAMPLE>
<SAMPLE><SAMPLETIME>600</SAMPLETIME>
<DEPTH>4.33</DEPTH>
<PRESSURE>67740</PRESSURE>
<TEMPERATURE>10</TEMPERATURE>
<BOOKMARK></BOOKMARK>
<SACRATE>16.95</SACRATE>
<CYLPRESS>67740</CYLPRESS>
</SAMPLE>
<SAMPLE><SAMPLETIME>620</SAMPLETIME>
<DEPTH>3.93</DEPTH>
<PRESSURE>67200</PRESSURE>
<TEMPERATURE>10</TEMPERATURE>
<BOOKMARK></BOOKMARK>
<SACRATE>13.59</SACRATE>
<CYLPRESS>67200</CYLPRESS>
</SAMPLE>
<SAMPLE><SAMPLETIME>640</SAMPLETIME>
<DEPTH>4.08</DEPTH>
<PRESSURE>66590</PRESSURE>
<TEMPERATURE>10</TEMPERATURE>
<BOOKMARK></BOOKMARK>
<SACRATE>12.86</SACRATE>
<CYLPRESS>66590</CYLPRESS>
</SAMPLE>
<SAMPLE><SAMPLETIME>660</SAMPLETIME>
<DEPTH>4.3</DEPTH>
<PRESSURE>66140</PRESSURE>
<TEMPERATURE>10</TEMPERATURE>
<BOOKMARK></BOOKMARK>
<SACRATE>15.78</SACRATE>
<CYLPRESS>66140</CYLPRESS>
</SAMPLE>
<SAMPLE><SAMPLETIME>680</SAMPLETIME>
<DEPTH>4.11</DEPTH>
<PRESSURE>65790</PRESSURE>
<TEMPERATURE>10</TEMPERATURE>
<BOOKMARK></BOOKMARK>
<SACRATE>15.72</SACRATE>
<CYLPRESS>65790</CYLPRESS>
</SAMPLE>
<SAMPLE><SAMPLETIME>700</SAMPLETIME>
<DEPTH>3.6</DEPTH>
<PRESSURE>64830</PRESSURE>
<TEMPERATURE>10</TEMPERATURE>
<BOOKMARK></BOOKMARK>
<SACRATE>16.47</SACRATE>
<CYLPRESS>64830</CYLPRESS>
</SAMPLE>
<SAMPLE><SAMPLETIME>720</SAMPLETIME>
<DEPTH>2.56</DEPTH>
<PRESSURE>64340</PRESSURE>
<TEMPERATURE>10</TEMPERATURE>
<BOOKMARK></BOOKMARK>
<SACRATE>16.9</SACRATE>
<CYLPRESS>64340</CYLPRESS>
</SAMPLE>
<SAMPLE><SAMPLETIME>740</SAMPLETIME>
<DEPTH>1.44</DEPTH>
<PRESSURE>63700</PRESSURE>
<TEMPERATURE>10</TEMPERATURE>
<BOOKMARK></BOOKMARK>
<SACRATE>20.29</SACRATE>
<CYLPRESS>63700</CYLPRESS>
</SAMPLE>
<SAMPLE><SAMPLETIME>749</SAMPLETIME>
<DEPTH>1.2</DEPTH>
<PRESSURE>0</PRESSURE>
<TEMPERATURE>0</TEMPERATURE>
<BOOKMARK>Surface</BOOKMARK>
<BOOKMARKTYPE>125</BOOKMARKTYPE>
<SACRATE>0</SACRATE>
<CYLPRESS>0</CYLPRESS>
<OXYGENPCT>0</OXYGENPCT>
</SAMPLE>
</MSG>
</SUUNTO>
